pydoctest/__init__.py
pydoctest/configuration.py
pydoctest/exceptions.py
pydoctest/logging.py
pydoctest/main.py
pydoctest/utilities.py
pydoctest/validation.py
pydoctest/version.py
pydoctest/parsers/__init__.py
pydoctest/parsers/google_parser.py
pydoctest/parsers/numpy_parser.py
pydoctest/parsers/parser.py
pydoctest/parsers/sphinx_parser.py
pydoctest/reporters/__init__.py
pydoctest/reporters/json_reporter.py
pydoctest/reporters/reporter.py
pydoctest/reporters/text_reporter.py
tests/__init__.py
tests/test_suite.py
tests/test_class/__init__.py
tests/test_class/correct_class.py
tests/test_class/counts_class.py
tests/test_class/enum_in_module.py
tests/test_class/incorrect_class.py
tests/test_class/nodocstring_class.py
tests/test_class/raises_class.py
tests/test_class/test_class.py
tests/test_parsers/__init__.py
tests/test_parsers/google_class.py
tests/test_parsers/numpy_class.py
tests/test_parsers/sphinx_class.py
tests/test_parsers/test_google_parser.py
tests/test_parsers/test_numpy_parser.py
tests/test_parsers/test_sphinx_parser.py
tests/test_ranges/__init__.py
tests/test_ranges/example_class.py
tests/test_ranges/test_ranges.py
pydoctest-0.2.0.dist-info/LICENSE
pydoctest-0.2.0.dist-info/METADATA
pydoctest-0.2.0.dist-info/WHEEL
pydoctest-0.2.0.dist-info/entry_points.txt
pydoctest-0.2.0.dist-info/top_level.txt
pydoctest-0.2.0.dist-info/RECORD
