Metadata-Version: 2.1
Name: pydoctest
Version: 0.2.0
Summary: Test if doctype types match signatures
Home-page: https://github.com/jepperaskdk/pydoctest
Author: Jeppe Rask
Author-email: jepperaskdk@gmail.com
License: UNKNOWN
Project-URL: Bug Tracker, https://github.com/jepperaskdk/pydoctest/issues
Platform: UNKNOWN
Requires-Python: >=3.6
